datagnosis/__init__.py
datagnosis/logger.py
datagnosis/version.py
datagnosis/plugins/__init__.py
datagnosis/plugins/utils.py
datagnosis/plugins/core/__init__.py
datagnosis/plugins/core/datahandler.py
datagnosis/plugins/core/plugin.py
datagnosis/plugins/core/utils.py
datagnosis/plugins/core/models/confident_learning.py
datagnosis/plugins/core/models/dataiq_maps_torch.py
datagnosis/plugins/core/models/image_nets.py
datagnosis/plugins/core/models/simple_mlp.py
datagnosis/plugins/generic/__init__.py
datagnosis/plugins/generic/plugin_aum.py
datagnosis/plugins/generic/plugin_conf_agree.py
datagnosis/plugins/generic/plugin_confident_learning.py
datagnosis/plugins/generic/plugin_data_iq.py
datagnosis/plugins/generic/plugin_data_maps.py
datagnosis/plugins/generic/plugin_el2n.py
datagnosis/plugins/generic/plugin_forgetting.py
datagnosis/plugins/generic/plugin_grand.py
datagnosis/plugins/generic/plugin_large_loss.py
datagnosis/plugins/generic/plugin_prototypicality.py
datagnosis/plugins/generic/plugin_vog.py
datagnosis/plugins/images/__init__.py
datagnosis/plugins/images/plugin_allsh.py
datagnosis/utils/__init__.py
datagnosis/utils/constants.py
datagnosis/utils/reproducibility.py
datagnosis/utils/datasets/images/__init__.py
datagnosis/utils/datasets/images/cifar.py
datagnosis/utils/datasets/images/mnist.py
datagnosis-0.0.3.dist-info/LICENSE.txt
datagnosis-0.0.3.dist-info/METADATA
datagnosis-0.0.3.dist-info/WHEEL
datagnosis-0.0.3.dist-info/top_level.txt
datagnosis-0.0.3.dist-info/RECORD
