Metadata-Version: 2.1
Name: datagnosis
Version: 0.0.3
Summary: A Data-Centric AI library for measuring hardness categorization.
Author: robsdavis
Author-email: robsdavis473@gmail.com
License: Apache-2.0
Platform: any
Classifier: Development Status :: 4 - Beta
Classifier: Programming Language :: Python :: 3
Classifier: Topic :: Scientific/Engineering :: Artificial Intelligence
Classifier: Intended Audience :: Science/Research
Classifier: Operating System :: OS Independent
Requires-Python: >=3.8
License-File: LICENSE.txt
Requires-Dist: torch
Requires-Dist: torchvision
Requires-Dist: numpy
Requires-Dist: pandas
Requires-Dist: loguru
Requires-Dist: aum
Requires-Dist: augly
Requires-Dist: pydantic >=2.0.0
Requires-Dist: scikit-learn
Requires-Dist: seaborn
Requires-Dist: cloudpickle
Requires-Dist: importlib-metadata ; python_version < "3.8"
Provides-Extra: testing
Requires-Dist: setuptools ; extra == 'testing'
Requires-Dist: pytest ; extra == 'testing'
Requires-Dist: pytest-cov ; extra == 'testing'
Requires-Dist: jupyter ; extra == 'testing'
Requires-Dist: notebook ; extra == 'testing'
Requires-Dist: bandit ; extra == 'testing'
Requires-Dist: black ; extra == 'testing'
Requires-Dist: black-nb ; extra == 'testing'
Requires-Dist: darglint ; extra == 'testing'
Requires-Dist: doc8 ; extra == 'testing'
Requires-Dist: flake8 ; extra == 'testing'
Requires-Dist: isort ; extra == 'testing'
Requires-Dist: nbconvert ; extra == 'testing'
Requires-Dist: nbformat ; extra == 'testing'
Requires-Dist: pytest-benchmark ; extra == 'testing'
Requires-Dist: pytest-xdist[psutil] ; extra == 'testing'
Requires-Dist: pytest-xprocess ; extra == 'testing'
Requires-Dist: py ; extra == 'testing'
Requires-Dist: pre-commit ; extra == 'testing'
